[{"id":"8a81876904ee1978","type":"tab","label":"TTS STT LT NLU","disabled":false,"info":"","env":[]},{"id":"bcbfbdb1bbe9f503","type":"watson-text-to-speech","z":"8a81876904ee1978","name":"","lang":"en-GB","langhidden":"en-GB","langcustom":"NoCustomisationSetting","langcustomhidden":"","voice":"en-GB_JamesV3Voice","voicehidden":"en-GB_JamesV3Voice","format":"audio/wav","password":"","apikey":"9f6n1WlCRlfLCziCmkkWN8_dvQuuijeOtcYjj51jq0-h","payload-response":true,"service-endpoint":"https://api.us-south.text-to-speech.watson.cloud.ibm.com/instances/e19a3a6b-ae45-402c-b33e-e316bf0a2199","x":440,"y":200,"wires":[["0788ad410bf5d995"]]},{"id":"cc643b381113b73a","type":"ui_form","z":"8a81876904ee1978","name":"","label":"","group":"b9db7ebc0ffc2012","order":0,"width":0,"height":0,"options":[{"label":"Enter any text","value":"tex","type":"text","required":true,"rows":null}],"formValue":{"tex":""},"payload":"","submit":"submit","cancel":"cancel","topic":"topic","topicType":"msg","splitLayout":"","className":"","x":70,"y":200,"wires":[["6fe5f583315838b4"]]},{"id":"6fe5f583315838b4","type":"function","z":"8a81876904ee1978","name":"","func":"msg.payload = msg.payload.tex;\nreturn msg;","outputs":1,"noerr":0,"initialize":"","finalize":"","libs":[],"x":240,"y":200,"wires":[["bcbfbdb1bbe9f503","7855fd58cb42f689"]]},{"id":"0788ad410bf5d995","type":"ui_audio","z":"8a81876904ee1978","name":"","group":"b9db7ebc0ffc2012","voice":"Google UK English Female","always":"","x":690,"y":200,"wires":[]},{"id":"7b3229fecd62e3f2","type":"watson-speech-to-text","z":"8a81876904ee1978","name":"","alternatives":1,"speakerlabels":true,"smartformatting":false,"lang":"en-GB","langhidden":"en-GB","langcustom":"NoCustomisationSetting","langcustomhidden":"","custom-weight":"0.5","band":"BroadbandModel","bandhidden":"","keywords":"","keywords-threshold":"0.5","word-confidence":false,"password":"","apikey":"p-8fbbjI-NHhaNXnqeDvRp99Smf0kDD_tU6eK_u_j5xn","payload-response":true,"streaming-mode":false,"streaming-mute":true,"auto-connect":false,"discard-listening":false,"disable-precheck":false,"service-endpoint":"https://api.us-south.speech-to-text.watson.cloud.ibm.com/instances/e5b491cd-212f-421f-863d-362d64ce06f2","x":340,"y":320,"wires":[["69c5273fa7c03502","edb768e6a913d6f7"]]},{"id":"78220cdaad77560c","type":"ui_microphone","z":"8a81876904ee1978","name":"","group":"b9db7ebc0ffc2012","order":2,"width":0,"height":0,"maxLength":5,"maxRecogLength":5,"timeslice":0,"press":"click","mode":"audio","interimResults":false,"x":100,"y":340,"wires":[["7b3229fecd62e3f2"]]},{"id":"69c5273fa7c03502","type":"ui_text","z":"8a81876904ee1978","group":"b9db7ebc0ffc2012","order":3,"width":0,"height":0,"name":"","label":"Source Text","format":"{{msg.payload}}","layout":"row-spread","className":"","x":640,"y":340,"wires":[]},{"id":"edb768e6a913d6f7","type":"watson-translator","z":"8a81876904ee1978","name":"","action":"translate","basemodel":"ar-en","domain":"general","srclang":"en","destlang":"de","password":"","apikey":"1h-B6tSaUFSowq1TIOtSiZvDt-ZxRFdKdrYkxZoxIUs8","custom":"","domainhidden":"general","srclanghidden":"en","destlanghidden":"de","basemodelhidden":"ar-en","customhidden":"","filetype":"forcedglossary","trainid":"","lgparams2":true,"service-endpoint":"https://api.us-south.language-translator.watson.cloud.ibm.com/instances/d9989a49-9326-4393-9c38-d8a05fa62c9d","x":560,"y":420,"wires":[["d97ef96ab5feb6af","a8ba504ed6f16483"]]},{"id":"d97ef96ab5feb6af","type":"ui_text","z":"8a81876904ee1978","group":"b9db7ebc0ffc2012","order":4,"width":0,"height":0,"name":"","label":"Translated Text","format":"{{msg.payload}}","layout":"row-spread","className":"","x":790,"y":400,"wires":[]},{"id":"a8ba504ed6f16483","type":"ui_audio","z":"8a81876904ee1978","name":"","group":"b9db7ebc0ffc2012","voice":"Google UK English Female","always":"","x":790,"y":460,"wires":[]},{"id":"7855fd58cb42f689","type":"natural-language-understanding","z":"8a81876904ee1978","name":"","categories":false,"limitcategories":"3","concepts":false,"maxconcepts":"8","doc-emotion":true,"doc-emotion-target":"","doc-sentiment":true,"doc-sentiment-target":"","entity":false,"entity-emotion":false,"entity-sentiment":false,"maxentities":"50","keyword":false,"keyword-emotion":false,"keyword-sentiment":false,"maxkeywords":"50","metadata":false,"relation":false,"semantic":false,"semantic-entities":false,"semantic-keywords":false,"maxsemantics":"50","limittextcharacters":"0","syntax":false,"syntax-sentences":false,"syntax-tokens-lemma":false,"syntax-tokens-pos":false,"service-endpoint":"https://api.us-south.natural-language-understanding.watson.cloud.ibm.com/instances/37796b69-345d-4e19-b4a1-bd98e899e0e3","credentials":{},"x":480,"y":80,"wires":[["5adf522b259a7f55"]]},{"id":"5adf522b259a7f55","type":"debug","z":"8a81876904ee1978","name":"","active":true,"tosidebar":true,"console":false,"tostatus":false,"complete":"true","targetType":"full","statusVal":"","statusType":"auto","x":780,"y":80,"wires":[]},{"id":"b9db7ebc0ffc2012","type":"ui_group","name":"Enter text values","tab":"89a5bb8b1df25207","order":1,"disp":true,"width":"6","collapse":false,"className":""},{"id":"89a5bb8b1df25207","type":"ui_tab","name":"Text analysis","icon":"dashboard","disabled":false,"hidden":false}]